package r.k.d.m.p;

class j$x
{
    static final /* synthetic */ int[] sqe;
    public static final boolean sqo;
    public static final int sqt;
    public static final boolean sqn;
    static final /* synthetic */ int[] sqe;
    public static final boolean sqo;
    public static final int sqt;
    public static final boolean sqn;
    
    static {
        // 
        // This method could not be decompiled.
        // 
        // Could not show original bytecode, likely due to the same error.
        // 
        throw new IllegalStateException("An error occurred while decompiling this method.");
    }
    
    static {
        // 
        // This method could not be decompiled.
        // 
        // Original Bytecode:
        // 
        //     1: goto            5
        //     4: return         
        //     5: nop            
        //     6: nop            
        //     7: invokestatic    r/k/d/m/p/j$s.values:()[Lr/k/d/m/p/j$s;
        //    10: arraylength    
        //    11: newarray        I
        //    13: putstatic       r/k/d/m/p/j$x.sqe:[I
        //    16: getstatic       r/k/d/m/p/j$x.sqe:[I
        //    19: getstatic       r/k/d/m/p/j$s.gt:Lr/k/d/m/p/j$s;
        //    22: invokevirtual   r/k/d/m/p/j$s.ordinal:()I
        //    25: iconst_1       
        //    26: iastore        
        //    27: nop            
        //    28: getstatic       r/k/d/m/p/j$x.sqe:[I
        //    31: getstatic       r/k/d/m/p/j$s.gn:Lr/k/d/m/p/j$s;
        //    34: invokevirtual   r/k/d/m/p/j$s.ordinal:()I
        //    37: iconst_2       
        //    38: iastore        
        //    39: nop            
        //    40: astore_0       
        //    41: getstatic       r/k/d/m/p/j$x.sqe:[I
        //    44: getstatic       r/k/d/m/p/j$s.gi:Lr/k/d/m/p/j$s;
        //    47: invokevirtual   r/k/d/m/p/j$s.ordinal:()I
        //    50: iconst_3       
        //    51: iastore        
        //    52: nop            
        //    53: astore_0       
        //    54: getstatic       r/k/d/m/p/j$x.sqe:[I
        //    57: getstatic       r/k/d/m/p/j$s.gp:Lr/k/d/m/p/j$s;
        //    60: invokevirtual   r/k/d/m/p/j$s.ordinal:()I
        //    63: iconst_4       
        //    64: iastore        
        //    65: nop            
        //    66: astore_0       
        //    67: return         
        //    Exceptions:
        //  Try           Handler
        //  Start  End    Start  End    Type                        
        //  -----  -----  -----  -----  ----------------------------
        //  16     27     28     40     Ljava/lang/NoSuchFieldError;
        //  28     39     40     68     Ljava/lang/NoSuchFieldError;
        //  41     52     53     68     Ljava/lang/NoSuchFieldError;
        //  54     65     66     68     Ljava/lang/NoSuchFieldError;
        // 
        throw new IllegalStateException("An error occurred while decompiling this method.");
    }
}
