package r.k.c.o;

public class y extends h
{
    public static final boolean sue;
    public static final int suo;
    public static final boolean sut;
    
    public y() {
        super();
    }
    
    @Override
    public void li() {
        // 
        // This method could not be decompiled.
        // 
        // Original Bytecode:
        // 
        //     1: goto            5
        //     4: return         
        //     5: nop            
        //     6: nop            
        //     7: invokestatic    r/k/c/c/j.h:()Ljava/util/ArrayList;
        //    10: invokevirtual   java/util/ArrayList.iterator:()Ljava/util/Iterator;
        //    13: astore_1       
        //    14: aload_1        
        //    15: invokeinterface java/util/Iterator.hasNext:()Z
        //    20: ifeq            1163
        //    23: aload_1        
        //    24: invokeinterface java/util/Iterator.next:()Ljava/lang/Object;
        //    29: checkcast       Lr/k/c/c/j;
        //    32: astore_2       
        //    33: aconst_null    
        //    34: astore_3       
        //    35: aload_2        
        //    36: invokevirtual   r/k/c/c/j.kl:()Ljava/util/ArrayList;
        //    39: invokestatic    java/util/Objects.requireNonNull:(Ljava/lang/Object;)Ljava/lang/Object;
        //    42: checkcast       Ljava/util/ArrayList;
        //    45: invokevirtual   java/util/ArrayList.iterator:()Ljava/util/Iterator;
        //    48: astore          4
        //    50: aload           4
        //    52: invokeinterface java/util/Iterator.hasNext:()Z
        //    57: ifeq            1162
        //    60: aload           4
        //    62: invokeinterface java/util/Iterator.next:()Ljava/lang/Object;
        //    67: checkcast       Lr/k/c/c/h;
        //    70: astore          5
        //    72: getstatic       r/k/c/n.sht:I
        //    75: aload           5
        //    77: getfield        r/k/c/c/h.en:I
        //    80: isub           
        //    81: i2d            
        //    82: aload           5
        //    84: getfield        r/k/c/c/h.ep:I
        //    87: invokestatic    java/lang/Integer.valueOf:(I)Ljava/lang/Integer;
        //    90: invokevirtual   java/lang/Number.doubleValue:()D
        //    93: ddiv           
        //    94: invokestatic    java/lang/Double.valueOf:(D)Ljava/lang/Double;
        //    97: astore          6
        //    99: getstatic       r/k/c/o/y$i.wa:[I
        //   102: aload           5
        //   104: invokevirtual   r/k/c/c/h.sw:()Lr/k/d/o/m;
        //   107: invokevirtual   r/k/d/o/m.yq:()Lr/k/d/o/y;
        //   110: invokevirtual   r/k/d/o/y.ordinal:()I
        //   113: iaload         
        //   114: tableswitch {
        //                2: 152
        //                3: 337
        //                4: 494
        //                5: 582
        //                6: 756
        //                7: 930
        //          default: 1111
        //        }
        //   152: aload           5
        //   154: getfield        r/k/c/c/h.eo:Z
        //   157: ifeq            291
        //   160: aload           5
        //   162: ldc             "Bind: ..."
        //   164: putfield        r/k/c/c/h.ef:Ljava/lang/String;
        //   167: invokestatic    org/lwjgl/input/Keyboard.getEventKeyState:()Z
        //   170: ifeq            235
        //   173: aload           5
        //   175: invokevirtual   r/k/c/c/h.sw:()Lr/k/d/o/m;
        //   178: invokestatic    org/lwjgl/input/Keyboard.getEventKey:()I
        //   181: invokestatic    org/lwjgl/input/Keyboard.getKeyName:(I)Ljava/lang/String;
        //   184: invokevirtual   r/k/d/o/m.d:(Ljava/lang/Object;)V
        //   187: aload           5
        //   189: new             Ljava/lang/StringBuilder;
        //   192: dup            
        //   193: invokespecial   java/lang/StringBuilder.<init>:()V
        //   196: ldc             "Bind: "
        //   198: invokevirtual   java/lang/StringBuilder.append:(Ljava/lang/String;)Ljava/lang/StringBuilder;
        //   201: aload           5
        //   203: invokevirtual   r/k/c/c/h.sw:()Lr/k/d/o/m;
        //   206: invokevirtual   r/k/d/o/m.yv:()Ljava/lang/Object;
        //   209: invokevirtual   java/lang/StringBuilder.append:(Ljava/lang/Object;)Ljava/lang/StringBuilder;
        //   212: invokevirtual   java/lang/StringBuilder.toString:()Ljava/lang/String;
        //   215: putfield        r/k/c/c/h.ef:Ljava/lang/String;
        //   218: aload           5
        //   220: iconst_0       
        //   221: putfield        r/k/c/c/h.eo:Z
        //   224: aload_2        
        //   225: iconst_0       
        //   226: putfield        r/k/c/c/j.eo:Z
        //   229: aload           5
        //   231: iconst_1       
        //   232: putfield        r/k/c/c/h.wu:Z
        //   235: aload           5
        //   237: getfield        r/k/c/c/h.et:Z
        //   240: ifeq            322
        //   243: aload           5
        //   245: invokevirtual   r/k/c/c/h.sw:()Lr/k/d/o/m;
        //   248: ldc             "NONE"
        //   250: invokevirtual   r/k/d/o/m.d:(Ljava/lang/Object;)V
        //   253: aload           5
        //   255: new             Ljava/lang/StringBuilder;
        //   258: dup            
        //   259: invokespecial   java/lang/StringBuilder.<init>:()V
        //   262: ldc             "Bind: "
        //   264: invokevirtual   java/lang/StringBuilder.append:(Ljava/lang/String;)Ljava/lang/StringBuilder;
        //   267: aload           5
        //   269: invokevirtual   r/k/c/c/h.sw:()Lr/k/d/o/m;
        //   272: invokevirtual   r/k/d/o/m.yv:()Ljava/lang/Object;
        //   275: invokevirtual   java/lang/StringBuilder.append:(Ljava/lang/Object;)Ljava/lang/StringBuilder;
        //   278: invokevirtual   java/lang/StringBuilder.toString:()Ljava/lang/String;
        //   281: putfield        r/k/c/c/h.ef:Ljava/lang/String;
        //   284: aload           5
        //   286: iconst_0       
        //   287: putfield        r/k/c/c/h.eo:Z
        //   290: nop            
        //   291: aload           5
        //   293: new             Ljava/lang/StringBuilder;
        //   296: dup            
        //   297: invokespecial   java/lang/StringBuilder.<init>:()V
        //   300: ldc             "Bind: "
        //   302: invokevirtual   java/lang/StringBuilder.append:(Ljava/lang/String;)Ljava/lang/StringBuilder;
        //   305: aload           5
        //   307: invokevirtual   r/k/c/c/h.sw:()Lr/k/d/o/m;
        //   310: invokevirtual   r/k/d/o/m.yv:()Ljava/lang/Object;
        //   313: invokevirtual   java/lang/StringBuilder.append:(Ljava/lang/Object;)Ljava/lang/StringBuilder;
        //   316: invokevirtual   java/lang/StringBuilder.toString:()Ljava/lang/String;
        //   319: putfield        r/k/c/c/h.ef:Ljava/lang/String;
        //   322: aload           5
        //   324: getfield        r/k/c/c/h.et:Z
        //   327: ifeq            1111
        //   330: aload           5
        //   332: iconst_0       
        //   333: putfield        r/k/c/c/h.et:Z
        //   336: nop            
        //   337: aload           5
        //   339: getfield        r/k/c/c/h.eo:Z
        //   342: ifeq            448
        //   345: iconst_0       
        //   346: istore          7
        //   348: iload           7
        //   350: aload           5
        //   352: invokevirtual   r/k/c/c/h.sw:()Lr/k/d/o/m;
        //   355: invokevirtual   r/k/d/o/m.yt:()[Ljava/lang/Enum;
        //   358: arraylength    
        //   359: if_icmpge       442
        //   362: aload           5
        //   364: invokevirtual   r/k/c/c/h.sw:()Lr/k/d/o/m;
        //   367: invokevirtual   r/k/d/o/m.yt:()[Ljava/lang/Enum;
        //   370: iload           7
        //   372: aaload         
        //   373: aload           5
        //   375: invokevirtual   r/k/c/c/h.sw:()Lr/k/d/o/m;
        //   378: invokevirtual   r/k/d/o/m.yv:()Ljava/lang/Object;
        //   381: invokevirtual   java/lang/Enum.equals:(Ljava/lang/Object;)Z
        //   384: ifeq            438
        //   387: aload           5
        //   389: invokevirtual   r/k/c/c/h.sw:()Lr/k/d/o/m;
        //   392: aload           5
        //   394: invokevirtual   r/k/c/c/h.sw:()Lr/k/d/o/m;
        //   397: invokevirtual   r/k/d/o/m.yt:()[Ljava/lang/Enum;
        //   400: aload           5
        //   402: invokevirtual   r/k/c/c/h.sw:()Lr/k/d/o/m;
        //   405: invokevirtual   r/k/d/o/m.yt:()[Ljava/lang/Enum;
        //   408: arraylength    
        //   409: iconst_1       
        //   410: isub           
        //   411: aaload         
        //   412: invokevirtual   r/k/d/o/m.d:(Ljava/lang/Object;)V
        //   415: nop            
        //   416: aload           5
        //   418: invokevirtual   r/k/c/c/h.sw:()Lr/k/d/o/m;
        //   421: aload           5
        //   423: invokevirtual   r/k/c/c/h.sw:()Lr/k/d/o/m;
        //   426: invokevirtual   r/k/d/o/m.yt:()[Ljava/lang/Enum;
        //   429: iload           7
        //   431: iconst_1       
        //   432: isub           
        //   433: aaload         
        //   434: invokevirtual   r/k/d/o/m.d:(Ljava/lang/Object;)V
        //   437: nop            
        //   438: iinc            7, 1
        //   441: nop            
        //   442: aload           5
        //   444: iconst_0       
        //   445: putfield        r/k/c/c/h.eo:Z
        //   448: aload           5
        //   450: new             Ljava/lang/StringBuilder;
        //   453: dup            
        //   454: invokespecial   java/lang/StringBuilder.<init>:()V
        //   457: aload           5
        //   459: invokevirtual   r/k/c/c/h.sw:()Lr/k/d/o/m;
        //   462: invokevirtual   r/k/d/o/m.o:()Ljava/lang/String;
        //   465: invokevirtual   java/lang/StringBuilder.append:(Ljava/lang/String;)Ljava/lang/StringBuilder;
        //   468: ldc             ": "
        //   470: invokevirtual   java/lang/StringBuilder.append:(Ljava/lang/String;)Ljava/lang/StringBuilder;
        //   473: aload           5
        //   475: invokevirtual   r/k/c/c/h.sw:()Lr/k/d/o/m;
        //   478: invokevirtual   r/k/d/o/m.yv:()Ljava/lang/Object;
        //   481: invokevirtual   java/lang/Object.toString:()Ljava/lang/String;
        //   484: invokevirtual   java/lang/StringBuilder.append:(Ljava/lang/String;)Ljava/lang/StringBuilder;
        //   487: invokevirtual   java/lang/StringBuilder.toString:()Ljava/lang/String;
        //   490: putfield        r/k/c/c/h.ef:Ljava/lang/String;
        //   493: nop            
        //   494: aload           5
        //   496: getfield        r/k/c/c/h.eo:Z
        //   499: ifeq            539
        //   502: aload           5
        //   504: invokevirtual   r/k/c/c/h.sw:()Lr/k/d/o/m;
        //   507: aload           5
        //   509: invokevirtual   r/k/c/c/h.sw:()Lr/k/d/o/m;
        //   512: invokevirtual   r/k/d/o/m.yv:()Ljava/lang/Object;
        //   515: checkcast       Ljava/lang/Boolean;
        //   518: invokevirtual   java/lang/Boolean.booleanValue:()Z
        //   521: ifne            526
        //   524: iconst_1       
        //   525: nop            
        //   526: iconst_0       
        //   527: invokestatic    java/lang/Boolean.valueOf:(Z)Ljava/lang/Boolean;
        //   530: invokevirtual   r/k/d/o/m.d:(Ljava/lang/Object;)V
        //   533: aload           5
        //   535: iconst_0       
        //   536: putfield        r/k/c/c/h.eo:Z
        //   539: aload           5
        //   541: new             Ljava/lang/StringBuilder;
        //   544: dup            
        //   545: invokespecial   java/lang/StringBuilder.<init>:()V
        //   548: aload           5
        //   550: invokevirtual   r/k/c/c/h.sw:()Lr/k/d/o/m;
        //   553: invokevirtual   r/k/d/o/m.o:()Ljava/lang/String;
        //   556: invokevirtual   java/lang/StringBuilder.append:(Ljava/lang/String;)Ljava/lang/StringBuilder;
        //   559: ldc             ": "
        //   561: invokevirtual   java/lang/StringBuilder.append:(Ljava/lang/String;)Ljava/lang/StringBuilder;
        //   564: aload           5
        //   566: invokevirtual   r/k/c/c/h.sw:()Lr/k/d/o/m;
        //   569: invokevirtual   r/k/d/o/m.yv:()Ljava/lang/Object;
        //   572: invokevirtual   java/lang/StringBuilder.append:(Ljava/lang/Object;)Ljava/lang/StringBuilder;
        //   575: invokevirtual   java/lang/StringBuilder.toString:()Ljava/lang/String;
        //   578: putfield        r/k/c/c/h.ef:Ljava/lang/String;
        //   581: nop            
        //   582: aload           5
        //   584: getfield        r/k/c/c/h.eo:Z
        //   587: ifeq            602
        //   590: aload           5
        //   592: iconst_1       
        //   593: putfield        r/k/c/c/h.wu:Z
        //   596: aload           5
        //   598: iconst_0       
        //   599: putfield        r/k/c/c/h.eo:Z
        //   602: iconst_0       
        //   603: invokestatic    org/lwjgl/input/Mouse.isButtonDown:(I)Z
        //   606: ifne            615
        //   609: aload           5
        //   611: iconst_0       
        //   612: putfield        r/k/c/c/h.wu:Z
        //   615: aload           5
        //   617: getfield        r/k/c/c/h.wu:Z
        //   620: ifeq            703
        //   623: getstatic       r/k/c/n.sht:I
        //   626: aload           5
        //   628: getfield        r/k/c/c/h.en:I
        //   631: if_icmplt       703
        //   634: getstatic       r/k/c/n.sht:I
        //   637: aload           5
        //   639: getfield        r/k/c/c/h.en:I
        //   642: aload           5
        //   644: getfield        r/k/c/c/h.ep:I
        //   647: iadd           
        //   648: if_icmpgt       703
        //   651: aload           5
        //   653: invokevirtual   r/k/c/c/h.sw:()Lr/k/d/o/m;
        //   656: aload           6
        //   658: invokevirtual   java/lang/Number.doubleValue:()D
        //   661: aload           5
        //   663: invokevirtual   r/k/c/c/h.sw:()Lr/k/d/o/m;
        //   666: invokevirtual   r/k/d/o/m.yo:()Ljava/lang/Number;
        //   669: invokevirtual   java/lang/Number.doubleValue:()D
        //   672: aload           5
        //   674: invokevirtual   r/k/c/c/h.sw:()Lr/k/d/o/m;
        //   677: invokevirtual   r/k/d/o/m.ye:()Ljava/lang/Number;
        //   680: invokevirtual   java/lang/Number.doubleValue:()D
        //   683: dsub           
        //   684: dmul           
        //   685: aload           5
        //   687: invokevirtual   r/k/c/c/h.sw:()Lr/k/d/o/m;
        //   690: invokevirtual   r/k/d/o/m.ye:()Ljava/lang/Number;
        //   693: invokevirtual   java/lang/Number.doubleValue:()D
        //   696: dadd           
        //   697: invokestatic    java/lang/Double.valueOf:(D)Ljava/lang/Double;
        //   700: invokevirtual   r/k/d/o/m.d:(Ljava/lang/Object;)V
        //   703: aload           5
        //   705: new             Ljava/lang/StringBuilder;
        //   708: dup            
        //   709: invokespecial   java/lang/StringBuilder.<init>:()V
        //   712: aload           5
        //   714: invokevirtual   r/k/c/c/h.sw:()Lr/k/d/o/m;
        //   717: invokevirtual   r/k/d/o/m.o:()Ljava/lang/String;
        //   720: invokevirtual   java/lang/StringBuilder.append:(Ljava/lang/String;)Ljava/lang/StringBuilder;
        //   723: ldc             ": "
        //   725: invokevirtual   java/lang/StringBuilder.append:(Ljava/lang/String;)Ljava/lang/StringBuilder;
        //   728: aload           5
        //   730: invokevirtual   r/k/c/c/h.sw:()Lr/k/d/o/m;
        //   733: invokevirtual   r/k/d/o/m.yv:()Ljava/lang/Object;
        //   736: checkcast       Ljava/lang/Number;
        //   739: invokevirtual   java/lang/Number.doubleValue:()D
        //   742: iconst_2       
        //   743: invokestatic    r/k/b/r.d:(DI)D
        //   746: invokevirtual   java/lang/StringBuilder.append:(D)Ljava/lang/StringBuilder;
        //   749: invokevirtual   java/lang/StringBuilder.toString:()Ljava/lang/String;
        //   752: putfield        r/k/c/c/h.ef:Ljava/lang/String;
        //   755: nop            
        //   756: aload           5
        //   758: getfield        r/k/c/c/h.eo:Z
        //   761: ifeq            776
        //   764: aload           5
        //   766: iconst_1       
        //   767: putfield        r/k/c/c/h.wu:Z
        //   770: aload           5
        //   772: iconst_0       
        //   773: putfield        r/k/c/c/h.eo:Z
        //   776: iconst_0       
        //   777: invokestatic    org/lwjgl/input/Mouse.isButtonDown:(I)Z
        //   780: ifne            789
        //   783: aload           5
        //   785: iconst_0       
        //   786: putfield        r/k/c/c/h.wu:Z
        //   789: aload           5
        //   791: getfield        r/k/c/c/h.wu:Z
        //   794: ifeq            877
        //   797: getstatic       r/k/c/n.sht:I
        //   800: aload           5
        //   802: getfield        r/k/c/c/h.en:I
        //   805: if_icmplt       877
        //   808: getstatic       r/k/c/n.sht:I
        //   811: aload           5
        //   813: getfield        r/k/c/c/h.en:I
        //   816: aload           5
        //   818: getfield        r/k/c/c/h.ep:I
        //   821: iadd           
        //   822: if_icmpgt       877
        //   825: aload           5
        //   827: invokevirtual   r/k/c/c/h.sw:()Lr/k/d/o/m;
        //   830: aload           6
        //   832: invokevirtual   java/lang/Number.floatValue:()F
        //   835: aload           5
        //   837: invokevirtual   r/k/c/c/h.sw:()Lr/k/d/o/m;
        //   840: invokevirtual   r/k/d/o/m.yo:()Ljava/lang/Number;
        //   843: invokevirtual   java/lang/Number.floatValue:()F
        //   846: aload           5
        //   848: invokevirtual   r/k/c/c/h.sw:()Lr/k/d/o/m;
        //   851: invokevirtual   r/k/d/o/m.ye:()Ljava/lang/Number;
        //   854: invokevirtual   java/lang/Number.floatValue:()F
        //   857: fsub           
        //   858: fmul           
        //   859: aload           5
        //   861: invokevirtual   r/k/c/c/h.sw:()Lr/k/d/o/m;
        //   864: invokevirtual   r/k/d/o/m.ye:()Ljava/lang/Number;
        //   867: invokevirtual   java/lang/Number.floatValue:()F
        //   870: fadd           
        //   871: invokestatic    java/lang/Float.valueOf:(F)Ljava/lang/Float;
        //   874: invokevirtual   r/k/d/o/m.d:(Ljava/lang/Object;)V
        //   877: aload           5
        //   879: new             Ljava/lang/StringBuilder;
        //   882: dup            
        //   883: invokespecial   java/lang/StringBuilder.<init>:()V
        //   886: aload           5
        //   888: invokevirtual   r/k/c/c/h.sw:()Lr/k/d/o/m;
        //   891: invokevirtual   r/k/d/o/m.o:()Ljava/lang/String;
        //   894: invokevirtual   java/lang/StringBuilder.append:(Ljava/lang/String;)Ljava/lang/StringBuilder;
        //   897: ldc             ": "
        //   899: invokevirtual   java/lang/StringBuilder.append:(Ljava/lang/String;)Ljava/lang/StringBuilder;
        //   902: aload           5
        //   904: invokevirtual   r/k/c/c/h.sw:()Lr/k/d/o/m;
        //   907: invokevirtual   r/k/d/o/m.yv:()Ljava/lang/Object;
        //   910: checkcast       Ljava/lang/Number;
        //   913: invokevirtual   java/lang/Number.doubleValue:()D
        //   916: iconst_2       
        //   917: invokestatic    r/k/b/r.d:(DI)D
        //   920: invokevirtual   java/lang/StringBuilder.append:(D)Ljava/lang/StringBuilder;
        //   923: invokevirtual   java/lang/StringBuilder.toString:()Ljava/lang/String;
        //   926: putfield        r/k/c/c/h.ef:Ljava/lang/String;
        //   929: nop            
        //   930: aload           5
        //   932: getfield        r/k/c/c/h.eo:Z
        //   935: ifeq            950
        //   938: aload           5
        //   940: iconst_1       
        //   941: putfield        r/k/c/c/h.wu:Z
        //   944: aload           5
        //   946: iconst_0       
        //   947: putfield        r/k/c/c/h.eo:Z
        //   950: iconst_0       
        //   951: invokestatic    org/lwjgl/input/Mouse.isButtonDown:(I)Z
        //   954: ifne            963
        //   957: aload           5
        //   959: iconst_0       
        //   960: putfield        r/k/c/c/h.wu:Z
        //   963: aload           5
        //   965: getfield        r/k/c/c/h.wu:Z
        //   968: ifeq            1063
        //   971: getstatic       r/k/c/n.sht:I
        //   974: aload           5
        //   976: getfield        r/k/c/c/h.en:I
        //   979: if_icmplt       1063
        //   982: getstatic       r/k/c/n.sht:I
        //   985: aload           5
        //   987: getfield        r/k/c/c/h.en:I
        //   990: aload           5
        //   992: getfield        r/k/c/c/h.ep:I
        //   995: iadd           
        //   996: if_icmpgt       1063
        //   999: aload           6
        //  1001: invokevirtual   java/lang/Number.doubleValue:()D
        //  1004: aload           5
        //  1006: invokevirtual   r/k/c/c/h.sw:()Lr/k/d/o/m;
        //  1009: invokevirtual   r/k/d/o/m.yo:()Ljava/lang/Number;
        //  1012: invokevirtual   java/lang/Number.intValue:()I
        //  1015: aload           5
        //  1017: invokevirtual   r/k/c/c/h.sw:()Lr/k/d/o/m;
        //  1020: invokevirtual   r/k/d/o/m.ye:()Ljava/lang/Number;
        //  1023: invokevirtual   java/lang/Number.intValue:()I
        //  1026: isub           
        //  1027: i2d            
        //  1028: dmul           
        //  1029: aload           5
        //  1031: invokevirtual   r/k/c/c/h.sw:()Lr/k/d/o/m;
        //  1034: invokevirtual   r/k/d/o/m.ye:()Ljava/lang/Number;
        //  1037: invokevirtual   java/lang/Number.intValue:()I
        //  1040: i2d            
        //  1041: dadd           
        //  1042: invokestatic    java/lang/Double.valueOf:(D)Ljava/lang/Double;
        //  1045: astore          7
        //  1047: aload           5
        //  1049: invokevirtual   r/k/c/c/h.sw:()Lr/k/d/o/m;
        //  1052: aload           7
        //  1054: invokevirtual   java/lang/Number.intValue:()I
        //  1057: invokestatic    java/lang/Integer.valueOf:(I)Ljava/lang/Integer;
        //  1060: invokevirtual   r/k/d/o/m.d:(Ljava/lang/Object;)V
        //  1063: aload           5
        //  1065: new             Ljava/lang/StringBuilder;
        //  1068: dup            
        //  1069: invokespecial   java/lang/StringBuilder.<init>:()V
        //  1072: aload           5
        //  1074: invokevirtual   r/k/c/c/h.sw:()Lr/k/d/o/m;
        //  1077: invokevirtual   r/k/d/o/m.o:()Ljava/lang/String;
        //  1080: invokevirtual   java/lang/StringBuilder.append:(Ljava/lang/String;)Ljava/lang/StringBuilder;
        //  1083: ldc             ": "
        //  1085: invokevirtual   java/lang/StringBuilder.append:(Ljava/lang/String;)Ljava/lang/StringBuilder;
        //  1088: aload           5
        //  1090: invokevirtual   r/k/c/c/h.sw:()Lr/k/d/o/m;
        //  1093: invokevirtual   r/k/d/o/m.yv:()Ljava/lang/Object;
        //  1096: checkcast       Ljava/lang/Number;
        //  1099: invokevirtual   java/lang/Number.intValue:()I
        //  1102: invokevirtual   java/lang/StringBuilder.append:(I)Ljava/lang/StringBuilder;
        //  1105: invokevirtual   java/lang/StringBuilder.toString:()Ljava/lang/String;
        //  1108: putfield        r/k/c/c/h.ef:Ljava/lang/String;
        //  1111: aload           5
        //  1113: aload           5
        //  1115: invokevirtual   r/k/c/c/h.sb:()Lr/k/c/c/j;
        //  1118: getfield        r/k/c/c/j.en:I
        //  1121: aload           5
        //  1123: getfield        r/k/c/c/h.ep:I
        //  1126: iadd           
        //  1127: putfield        r/k/c/c/h.en:I
        //  1130: aload_3        
        //  1131: ifnull          1149
        //  1134: aload           5
        //  1136: aload_3        
        //  1137: getfield        r/k/c/c/y.ei:I
        //  1140: aload_3        
        //  1141: getfield        r/k/c/c/y.er:I
        //  1144: iadd           
        //  1145: putfield        r/k/c/c/h.ei:I
        //  1148: nop            
        //  1149: aload           5
        //  1151: aload_2        
        //  1152: getfield        r/k/c/c/j.ei:I
        //  1155: putfield        r/k/c/c/h.ei:I
        //  1158: aload           5
        //  1160: astore_3       
        //  1161: nop            
        //  1162: nop            
        //  1163: return         
        //    StackMapTable: 00 23 FF 00 04 00 0B 07 00 15 00 00 00 00 00 00 00 00 00 01 00 00 00 FF 00 08 00 0B 07 00 15 07 00 23 00 00 00 00 00 00 01 01 01 00 00 FF 00 23 00 0B 07 00 15 07 00 23 07 00 36 07 00 38 07 00 23 00 00 00 01 01 01 00 00 FF 00 65 00 0B 07 00 15 07 00 23 07 00 36 07 00 38 07 00 23 07 00 38 07 00 53 00 01 01 01 00 00 FB 00 52 37 1E 0E FF 00 0A 00 0B 07 00 15 07 00 23 07 00 36 07 00 38 07 00 23 07 00 38 07 00 53 01 01 01 01 00 00 FB 00 43 15 03 FF 00 05 00 0B 07 00 15 07 00 23 07 00 36 07 00 38 07 00 23 07 00 38 07 00 53 00 01 01 01 00 00 2D 5F 07 00 BA FF 00 00 00 0B 07 00 15 07 00 23 07 00 36 07 00 38 07 00 23 07 00 38 07 00 53 00 01 01 01 00 02 07 00 BA 01 0B 2A 13 0C FB 00 57 34 13 0C FB 00 57 34 13 0C FB 00 63 2F 25 08 FF 00 03 00 0B 07 00 15 07 00 23 07 00 36 07 00 38 07 00 23 00 00 00 01 01 01 00 00 FF 00 00 00 0B 07 00 15 07 00 23 00 00 00 00 00 00 01 01 01 00 00
        // 
        throw new IllegalStateException("An error occurred while decompiling this method.");
    }
}
