package r.k.b.u;

public class y$l
{
    private final double sil;
    private final double siy;
    private final y$l$s six;
    public static final boolean sik;
    public static final int siq;
    public static final boolean siv;
    
    public y$l(final double sil, final double siy, final y$l$s six) {
        this.sil = sil;
        this.siy = siy;
        this.six = six;
    }
    
    public double yu() {
        return this.sil;
    }
    
    public double yz() {
        return this.siy;
    }
    
    public y$l$s xq() {
        return this.six;
    }
    
    public boolean d(final y$l$s p0) {
        // 
        // This method could not be decompiled.
        // 
        // Original Bytecode:
        // 
        //     1: goto            6
        //     4: iconst_1       
        //     5: ireturn        
        //     6: nop            
        //     7: aload_0        
        //     8: getfield        r/k/b/u/y$l.six:Lr/k/b/u/y$l$s;
        //    11: aload_1        
        //    12: if_acmpne       17
        //    15: iconst_1       
        //    16: nop            
        //    17: iconst_0       
        //    18: ireturn        
        //    StackMapTable: 00 04 FF 00 04 00 05 07 00 07 07 00 0C 00 00 01 00 00 01 FF 00 0A 00 05 07 00 07 07 00 0C 01 00 01 00 00 40 01
        // 
        throw new IllegalStateException("An error occurred while decompiling this method.");
    }
}
