package r.k.p.m;

import r.k.p.c.y;

public class h extends r.k.p.c.h
{
    public static final boolean sol;
    public static final int soy;
    public static final boolean sox;
    
    public h() {
        super("Element Picker");
    }
    
    @Override
    public void d(final int p0, final int p1, final float p2) {
        // 
        // This method could not be decompiled.
        // 
        // Original Bytecode:
        // 
        //     1: goto            5
        //     4: return         
        //     5: nop            
        //     6: nop            
        //     7: getstatic       r/k/p/m/h.mc:Lnet/minecraft/client/Minecraft;
        //    10: getfield        net/minecraft/client/Minecraft.currentScreen:Lnet/minecraft/client/gui/GuiScreen;
        //    13: instanceof      Lr/k/p/m/m;
        //    16: ifeq            340
        //    19: getstatic       r/k/u.lsp:Lr/k/p/o;
        //    22: getfield        r/k/p/o.llz:Ljava/util/List;
        //    25: invokeinterface java/util/List.stream:()Ljava/util/stream/Stream;
        //    30: aload_0        
        //    31: invokedynamic   BootstrapMethod #0, test:(Lr/k/p/m/h;)Ljava/util/function/Predicate;
        //    36: invokeinterface java/util/stream/Stream.filter:(Ljava/util/function/Predicate;)Ljava/util/stream/Stream;
        //    41: invokestatic    java/util/stream/Collectors.toList:()Ljava/util/stream/Collector;
        //    44: invokeinterface java/util/stream/Stream.collect:(Ljava/util/stream/Collector;)Ljava/lang/Object;
        //    49: checkcast       Ljava/util/List;
        //    52: astore          4
        //    54: aload_0        
        //    55: invokevirtual   r/k/p/m/h.z:()Lr/k/b/i/h;
        //    58: aload           4
        //    60: invokeinterface java/util/List.size:()I
        //    65: getstatic       r/k/p/m/h.mc:Lnet/minecraft/client/Minecraft;
        //    68: getfield        net/minecraft/client/Minecraft.fontRenderer:Lnet/minecraft/client/gui/FontRenderer;
        //    71: getfield        net/minecraft/client/gui/FontRenderer.FONT_HEIGHT:I
        //    74: iconst_2       
        //    75: iadd           
        //    76: imul           
        //    77: iconst_2       
        //    78: isub           
        //    79: putfield        r/k/b/i/h.slo:I
        //    82: aload_0        
        //    83: invokevirtual   r/k/p/m/h.z:()Lr/k/b/i/h;
        //    86: getfield        r/k/b/i/h.slo:I
        //    89: aload_0        
        //    90: invokevirtual   r/k/p/m/h.z:()Lr/k/b/i/h;
        //    93: getfield        r/k/b/i/h.slt:I
        //    96: aload_0        
        //    97: invokevirtual   r/k/p/m/h.c:()Lr/k/b/i/h;
        //   100: getfield        r/k/b/i/h.slo:I
        //   103: aload_0        
        //   104: invokevirtual   r/k/p/m/h.c:()Lr/k/b/i/h;
        //   107: getfield        r/k/b/i/h.slt:I
        //   110: getstatic       java/awt/Color.BLACK:Ljava/awt/Color;
        //   113: invokevirtual   java/awt/Color.getRGB:()I
        //   116: invokestatic    r/k/b/u/m.l:(IIIII)V
        //   119: getstatic       r/k/p/m/h.mc:Lnet/minecraft/client/Minecraft;
        //   122: getfield        net/minecraft/client/Minecraft.fontRenderer:Lnet/minecraft/client/gui/FontRenderer;
        //   125: ldc             "Element Picket"
        //   127: aload_0        
        //   128: invokevirtual   r/k/p/m/h.z:()Lr/k/b/i/h;
        //   131: getfield        r/k/b/i/h.slo:I
        //   134: iconst_2       
        //   135: iadd           
        //   136: aload_0        
        //   137: invokevirtual   r/k/p/m/h.z:()Lr/k/b/i/h;
        //   140: getfield        r/k/b/i/h.slt:I
        //   143: iconst_2       
        //   144: iadd           
        //   145: getstatic       java/awt/Color.WHITE:Ljava/awt/Color;
        //   148: invokevirtual   java/awt/Color.getRGB:()I
        //   151: invokevirtual   net/minecraft/client/gui/FontRenderer.drawString:(Ljava/lang/String;III)I
        //   154: pop            
        //   155: getstatic       r/k/p/m/h.mc:Lnet/minecraft/client/Minecraft;
        //   158: getfield        net/minecraft/client/Minecraft.fontRenderer:Lnet/minecraft/client/gui/FontRenderer;
        //   161: getfield        net/minecraft/client/gui/FontRenderer.FONT_HEIGHT:I
        //   164: iconst_2       
        //   165: iadd           
        //   166: istore          5
        //   168: aload_0        
        //   169: invokevirtual   r/k/p/m/h.z:()Lr/k/b/i/h;
        //   172: getfield        r/k/b/i/h.slo:I
        //   175: iconst_2       
        //   176: iadd           
        //   177: aload_0        
        //   178: invokevirtual   r/k/p/m/h.z:()Lr/k/b/i/h;
        //   181: getfield        r/k/b/i/h.slt:I
        //   184: iconst_2       
        //   185: iadd           
        //   186: iload           5
        //   188: iadd           
        //   189: aload_0        
        //   190: invokevirtual   r/k/p/m/h.c:()Lr/k/b/i/h;
        //   193: getfield        r/k/b/i/h.slo:I
        //   196: iconst_2       
        //   197: isub           
        //   198: aload_0        
        //   199: invokevirtual   r/k/p/m/h.c:()Lr/k/b/i/h;
        //   202: getfield        r/k/b/i/h.slt:I
        //   205: iconst_2       
        //   206: isub           
        //   207: getstatic       java/awt/Color.WHITE:Ljava/awt/Color;
        //   210: invokevirtual   java/awt/Color.getRGB:()I
        //   213: invokestatic    r/k/b/u/m.l:(IIIII)V
        //   216: aload           4
        //   218: invokeinterface java/util/List.iterator:()Ljava/util/Iterator;
        //   223: astore          6
        //   225: aload           6
        //   227: invokeinterface java/util/Iterator.hasNext:()Z
        //   232: ifeq            319
        //   235: aload           6
        //   237: invokeinterface java/util/Iterator.next:()Ljava/lang/Object;
        //   242: checkcast       Lr/k/p/c/y;
        //   245: astore          7
        //   247: getstatic       r/k/p/m/h.mc:Lnet/minecraft/client/Minecraft;
        //   250: getfield        net/minecraft/client/Minecraft.fontRenderer:Lnet/minecraft/client/gui/FontRenderer;
        //   253: aload           7
        //   255: invokevirtual   r/k/p/c/y.o:()Ljava/lang/String;
        //   258: aload_0        
        //   259: invokevirtual   r/k/p/m/h.z:()Lr/k/b/i/h;
        //   262: getfield        r/k/b/i/h.slo:I
        //   265: iconst_2       
        //   266: iadd           
        //   267: aload_0        
        //   268: invokevirtual   r/k/p/m/h.z:()Lr/k/b/i/h;
        //   271: getfield        r/k/b/i/h.slt:I
        //   274: iload           5
        //   276: iadd           
        //   277: aload           7
        //   279: invokevirtual   r/k/p/c/y.u:()Z
        //   282: ifeq            292
        //   285: getstatic       java/awt/Color.GRAY:Ljava/awt/Color;
        //   288: invokevirtual   java/awt/Color.getRGB:()I
        //   291: nop            
        //   292: getstatic       java/awt/Color.WHITE:Ljava/awt/Color;
        //   295: invokevirtual   java/awt/Color.getRGB:()I
        //   298: invokevirtual   net/minecraft/client/gui/FontRenderer.drawString:(Ljava/lang/String;III)I
        //   301: pop            
        //   302: iload           5
        //   304: getstatic       r/k/p/m/h.mc:Lnet/minecraft/client/Minecraft;
        //   307: getfield        net/minecraft/client/Minecraft.fontRenderer:Lnet/minecraft/client/gui/FontRenderer;
        //   310: getfield        net/minecraft/client/gui/FontRenderer.FONT_HEIGHT:I
        //   313: iconst_2       
        //   314: iadd           
        //   315: iadd           
        //   316: istore          5
        //   318: nop            
        //   319: aload_0        
        //   320: invokevirtual   r/k/p/m/h.c:()Lr/k/b/i/h;
        //   323: iload           5
        //   325: getstatic       r/k/p/m/h.mc:Lnet/minecraft/client/Minecraft;
        //   328: getfield        net/minecraft/client/Minecraft.fontRenderer:Lnet/minecraft/client/gui/FontRenderer;
        //   331: getfield        net/minecraft/client/gui/FontRenderer.FONT_HEIGHT:I
        //   334: iadd           
        //   335: iconst_2       
        //   336: iadd           
        //   337: putfield        r/k/b/i/h.slt:I
        //   340: aload_0        
        //   341: invokevirtual   r/k/p/m/h.xf:()V
        //   344: return         
        //    StackMapTable: 00 08 FF 00 04 00 0B 07 00 1A 01 01 02 00 00 00 00 00 00 01 00 00 00 FF 00 4C 00 0B 07 00 1A 01 01 02 07 00 36 00 00 00 01 01 01 00 00 FF 00 8E 00 0B 07 00 1A 01 01 02 07 00 36 01 07 00 97 00 01 01 01 00 00 FF 00 42 00 0B 07 00 1A 01 01 02 07 00 36 01 07 00 97 07 00 AD 01 01 01 00 04 07 00 6B 07 00 AF 01 01 FF 00 05 00 0B 07 00 1A 01 01 02 07 00 36 01 07 00 97 07 00 AD 01 01 01 00 05 07 00 6B 07 00 AF 01 01 01 FF 00 14 00 0B 07 00 1A 01 01 02 07 00 36 01 07 00 97 00 01 01 01 00 00 FF 00 14 00 0B 07 00 1A 01 01 02 00 00 00 00 01 01 01 00 00
        // 
        throw new IllegalStateException("An error occurred while decompiling this method.");
    }
    
    @Override
    public void s(final int p0, final int p1, final int p2) {
        // 
        // This method could not be decompiled.
        // 
        // Original Bytecode:
        // 
        //     1: goto            5
        //     4: return         
        //     5: nop            
        //     6: nop            
        //     7: aload_0        
        //     8: iload_1        
        //     9: iload_2        
        //    10: iload_3        
        //    11: invokespecial   r/k/p/c/h.s:(III)V
        //    14: aload_0        
        //    15: iload_1        
        //    16: iload_2        
        //    17: invokevirtual   r/k/p/m/h.s:(II)Z
        //    20: ifeq            224
        //    23: getstatic       r/k/u.lsp:Lr/k/p/o;
        //    26: getfield        r/k/p/o.llz:Ljava/util/List;
        //    29: invokeinterface java/util/List.stream:()Ljava/util/stream/Stream;
        //    34: aload_0        
        //    35: invokedynamic   BootstrapMethod #1, test:(Lr/k/p/m/h;)Ljava/util/function/Predicate;
        //    40: invokeinterface java/util/stream/Stream.filter:(Ljava/util/function/Predicate;)Ljava/util/stream/Stream;
        //    45: invokestatic    java/util/stream/Collectors.toList:()Ljava/util/stream/Collector;
        //    48: invokeinterface java/util/stream/Stream.collect:(Ljava/util/stream/Collector;)Ljava/lang/Object;
        //    53: checkcast       Ljava/util/List;
        //    56: astore          4
        //    58: getstatic       r/k/p/m/h.mc:Lnet/minecraft/client/Minecraft;
        //    61: getfield        net/minecraft/client/Minecraft.fontRenderer:Lnet/minecraft/client/gui/FontRenderer;
        //    64: getfield        net/minecraft/client/gui/FontRenderer.FONT_HEIGHT:I
        //    67: iconst_2       
        //    68: iadd           
        //    69: istore          5
        //    71: aload           4
        //    73: invokeinterface java/util/List.iterator:()Ljava/util/Iterator;
        //    78: astore          6
        //    80: aload           6
        //    82: invokeinterface java/util/Iterator.hasNext:()Z
        //    87: ifeq            224
        //    90: aload           6
        //    92: invokeinterface java/util/Iterator.next:()Ljava/lang/Object;
        //    97: checkcast       Lr/k/p/c/y;
        //   100: astore          7
        //   102: iload_1        
        //   103: aload_0        
        //   104: invokevirtual   r/k/p/m/h.z:()Lr/k/b/i/h;
        //   107: getfield        r/k/b/i/h.slo:I
        //   110: iconst_2       
        //   111: iadd           
        //   112: if_icmplt       183
        //   115: iload_2        
        //   116: aload_0        
        //   117: invokevirtual   r/k/p/m/h.z:()Lr/k/b/i/h;
        //   120: getfield        r/k/b/i/h.slt:I
        //   123: iload           5
        //   125: iadd           
        //   126: if_icmplt       183
        //   129: iload_1        
        //   130: aload_0        
        //   131: invokevirtual   r/k/p/m/h.z:()Lr/k/b/i/h;
        //   134: getfield        r/k/b/i/h.slo:I
        //   137: iconst_2       
        //   138: iadd           
        //   139: getstatic       r/k/p/m/h.mc:Lnet/minecraft/client/Minecraft;
        //   142: getfield        net/minecraft/client/Minecraft.fontRenderer:Lnet/minecraft/client/gui/FontRenderer;
        //   145: aload           7
        //   147: invokevirtual   r/k/p/c/y.o:()Ljava/lang/String;
        //   150: invokevirtual   net/minecraft/client/gui/FontRenderer.getStringWidth:(Ljava/lang/String;)I
        //   153: iadd           
        //   154: if_icmpgt       183
        //   157: iload_2        
        //   158: aload_0        
        //   159: invokevirtual   r/k/p/m/h.z:()Lr/k/b/i/h;
        //   162: getfield        r/k/b/i/h.slt:I
        //   165: iload           5
        //   167: iadd           
        //   168: getstatic       r/k/p/m/h.mc:Lnet/minecraft/client/Minecraft;
        //   171: getfield        net/minecraft/client/Minecraft.fontRenderer:Lnet/minecraft/client/gui/FontRenderer;
        //   174: getfield        net/minecraft/client/gui/FontRenderer.FONT_HEIGHT:I
        //   177: iadd           
        //   178: if_icmpgt       183
        //   181: iconst_1       
        //   182: nop            
        //   183: iconst_0       
        //   184: istore          8
        //   186: iload           8
        //   188: ifeq            207
        //   191: aload           7
        //   193: aload           7
        //   195: invokevirtual   r/k/p/c/y.u:()Z
        //   198: ifne            203
        //   201: iconst_1       
        //   202: nop            
        //   203: iconst_0       
        //   204: invokevirtual   r/k/p/c/y.d:(Z)V
        //   207: iload           5
        //   209: getstatic       r/k/p/m/h.mc:Lnet/minecraft/client/Minecraft;
        //   212: getfield        net/minecraft/client/Minecraft.fontRenderer:Lnet/minecraft/client/gui/FontRenderer;
        //   215: getfield        net/minecraft/client/gui/FontRenderer.FONT_HEIGHT:I
        //   218: iconst_2       
        //   219: iadd           
        //   220: iadd           
        //   221: istore          5
        //   223: nop            
        //   224: return         
        //    StackMapTable: 00 0A FF 00 04 00 0C 07 00 1A 01 01 01 00 00 00 00 00 00 00 01 00 00 00 FF 00 01 00 0C 07 00 1A 01 01 01 00 00 00 00 00 01 01 01 00 00 FF 00 48 00 0C 07 00 1A 01 01 01 07 00 36 01 07 00 97 00 00 01 01 01 00 00 FF 00 66 00 0C 07 00 1A 01 01 01 07 00 36 01 07 00 97 07 00 AD 00 01 01 01 00 00 40 01 FF 00 12 00 0C 07 00 1A 01 01 01 07 00 36 01 07 00 97 07 00 AD 01 01 01 01 00 01 07 00 AD FF 00 00 00 0C 07 00 1A 01 01 01 07 00 36 01 07 00 97 07 00 AD 01 01 01 01 00 02 07 00 AD 01 02 FF 00 10 00 0C 07 00 1A 01 01 01 00 00 00 00 00 01 01 01 00 00
        // 
        throw new IllegalStateException("An error occurred while decompiling this method.");
    }
    
    private /* synthetic */ boolean d(final y p0) {
        // 
        // This method could not be decompiled.
        // 
        // Original Bytecode:
        // 
        //     1: goto            6
        //     4: iconst_0       
        //     5: ireturn        
        //     6: nop            
        //     7: aload_1        
        //     8: aload_0        
        //     9: if_acmpeq       14
        //    12: iconst_1       
        //    13: nop            
        //    14: iconst_0       
        //    15: ireturn        
        //    StackMapTable: 00 04 FF 00 04 00 05 07 00 1A 07 00 AD 00 00 01 00 00 01 FF 00 07 00 05 07 00 1A 07 00 AD 01 00 01 00 00 40 01
        // 
        throw new IllegalStateException("An error occurred while decompiling this method.");
    }
    
    private /* synthetic */ boolean s(final y p0) {
        // 
        // This method could not be decompiled.
        // 
        // Original Bytecode:
        // 
        //     1: goto            6
        //     4: iconst_1       
        //     5: ireturn        
        //     6: nop            
        //     7: aload_1        
        //     8: aload_0        
        //     9: if_acmpeq       14
        //    12: iconst_1       
        //    13: nop            
        //    14: iconst_0       
        //    15: ireturn        
        //    StackMapTable: 00 04 FF 00 04 00 05 07 00 1A 07 00 AD 00 00 01 00 00 01 FF 00 07 00 05 07 00 1A 07 00 AD 01 00 01 00 00 40 01
        // 
        throw new IllegalStateException("An error occurred while decompiling this method.");
    }
}
