package r.k.b.i;

import r.k.g.c;
import r.k.h;
import net.minecraft.entity.player.EntityPlayer;
import java.util.ArrayList;

public class p
{
    private static final String lyy;
    private static ArrayList<String> lyx;
    public static final boolean lyk;
    public static final int lyq;
    public static final boolean lyv;
    private static final String lyy;
    private static ArrayList<String> lyx;
    public static final boolean lyk;
    public static final int lyq;
    public static final boolean lyv;
    
    public p() {
        super();
    }
    
    public static boolean kr() {
        // 
        // This method could not be decompiled.
        // 
        // Original Bytecode:
        // 
        //     1: goto            6
        //     4: iconst_0       
        //     5: ireturn        
        //     6: nop            
        //     7: nop            
        //     8: getstatic       r/k/b/i/p.lyx:Ljava/util/ArrayList;
        //    11: ifnonnull       24
        //    14: new             Lr/k/b/i/p$i;
        //    17: dup            
        //    18: invokespecial   r/k/b/i/p$i.<init>:()V
        //    21: putstatic       r/k/b/i/p.lyx:Ljava/util/ArrayList;
        //    24: new             Ljava/io/PrintWriter;
        //    27: dup            
        //    28: getstatic       r/k/b/i/p.lyy:Ljava/lang/String;
        //    31: invokespecial   java/io/PrintWriter.<init>:(Ljava/lang/String;)V
        //    34: astore_0       
        //    35: aload_0        
        //    36: ldc             ""
        //    38: invokevirtual   java/io/PrintWriter.print:(Ljava/lang/String;)V
        //    41: aload_0        
        //    42: invokevirtual   java/io/PrintWriter.close:()V
        //    45: new             Ljava/io/BufferedWriter;
        //    48: dup            
        //    49: new             Ljava/io/FileWriter;
        //    52: dup            
        //    53: getstatic       r/k/b/i/p.lyy:Ljava/lang/String;
        //    56: invokespecial   java/io/FileWriter.<init>:(Ljava/lang/String;)V
        //    59: invokespecial   java/io/BufferedWriter.<init>:(Ljava/io/Writer;)V
        //    62: astore_1       
        //    63: getstatic       r/k/b/i/p.lyx:Ljava/util/ArrayList;
        //    66: invokevirtual   java/util/ArrayList.iterator:()Ljava/util/Iterator;
        //    69: astore_2       
        //    70: aload_2        
        //    71: invokeinterface java/util/Iterator.hasNext:()Z
        //    76: ifeq            99
        //    79: aload_2        
        //    80: invokeinterface java/util/Iterator.next:()Ljava/lang/Object;
        //    85: checkcast       Ljava/lang/String;
        //    88: astore_3       
        //    89: aload_1        
        //    90: aload_3        
        //    91: invokevirtual   java/io/BufferedWriter.write:(Ljava/lang/String;)V
        //    94: aload_1        
        //    95: invokevirtual   java/io/BufferedWriter.newLine:()V
        //    98: nop            
        //    99: aload_1        
        //   100: invokevirtual   java/io/BufferedWriter.flush:()V
        //   103: aload_1        
        //   104: invokevirtual   java/io/BufferedWriter.close:()V
        //   107: iconst_1       
        //   108: ireturn        
        //   109: astore_0       
        //   110: getstatic       java/lang/System.out:Ljava/io/PrintStream;
        //   113: new             Ljava/lang/StringBuilder;
        //   116: dup            
        //   117: invokespecial   java/lang/StringBuilder.<init>:()V
        //   120: ldc             "Could not write friends.txt: "
        //   122: invokevirtual   java/lang/StringBuilder.append:(Ljava/lang/String;)Ljava/lang/StringBuilder;
        //   125: aload_0        
        //   126: invokevirtual   java/lang/Exception.toString:()Ljava/lang/String;
        //   129: invokevirtual   java/lang/StringBuilder.append:(Ljava/lang/String;)Ljava/lang/StringBuilder;
        //   132: invokevirtual   java/lang/StringBuilder.toString:()Ljava/lang/String;
        //   135: invokevirtual   java/io/PrintStream.println:(Ljava/lang/String;)V
        //   138: aload_0        
        //   139: invokevirtual   java/lang/Exception.printStackTrace:()V
        //   142: getstatic       java/lang/System.out:Ljava/io/PrintStream;
        //   145: getstatic       r/k/b/i/p.lyx:Ljava/util/ArrayList;
        //   148: invokevirtual   java/io/PrintStream.println:(Ljava/lang/Object;)V
        //   151: iconst_0       
        //   152: ireturn        
        //    StackMapTable: 00 07 FF 00 04 00 07 00 00 00 00 00 00 01 00 00 01 FF 00 11 00 07 00 00 00 00 01 01 01 00 00 FF 00 2D 00 07 07 00 24 07 00 32 07 00 40 00 01 01 01 00 00 1C FF 00 09 00 07 00 00 00 00 01 01 01 00 01 07 00 1D FF 00 00 00 07 07 00 1D 00 00 00 01 01 01 00 00
        //    Exceptions:
        //  Try           Handler
        //  Start  End    Start  End    Type                 
        //  -----  -----  -----  -----  ---------------------
        //  24     99     109    153    Ljava/lang/Exception;
        //  99     108    109    153    Ljava/lang/Exception;
        // 
        throw new IllegalStateException("An error occurred while decompiling this method.");
    }
    
    public static boolean kf() {
        // 
        // This method could not be decompiled.
        // 
        // Could not show original bytecode, likely due to the same error.
        // 
        throw new IllegalStateException("An error occurred while decompiling this method.");
    }
    
    public p() {
        super();
    }
    
    public static boolean kr() {
        // 
        // This method could not be decompiled.
        // 
        // Original Bytecode:
        // 
        //     1: goto            6
        //     4: iconst_0       
        //     5: ireturn        
        //     6: nop            
        //     7: nop            
        //     8: getstatic       r/k/b/i/p.lyx:Ljava/util/ArrayList;
        //    11: ifnonnull       24
        //    14: new             Lr/k/b/i/p$i;
        //    17: dup            
        //    18: invokespecial   r/k/b/i/p$i.<init>:()V
        //    21: putstatic       r/k/b/i/p.lyx:Ljava/util/ArrayList;
        //    24: new             Ljava/io/PrintWriter;
        //    27: dup            
        //    28: getstatic       r/k/b/i/p.lyy:Ljava/lang/String;
        //    31: invokespecial   java/io/PrintWriter.<init>:(Ljava/lang/String;)V
        //    34: astore_0       
        //    35: aload_0        
        //    36: ldc             ""
        //    38: invokevirtual   java/io/PrintWriter.print:(Ljava/lang/String;)V
        //    41: aload_0        
        //    42: invokevirtual   java/io/PrintWriter.close:()V
        //    45: new             Ljava/io/BufferedWriter;
        //    48: dup            
        //    49: new             Ljava/io/FileWriter;
        //    52: dup            
        //    53: getstatic       r/k/b/i/p.lyy:Ljava/lang/String;
        //    56: invokespecial   java/io/FileWriter.<init>:(Ljava/lang/String;)V
        //    59: invokespecial   java/io/BufferedWriter.<init>:(Ljava/io/Writer;)V
        //    62: astore_1       
        //    63: getstatic       r/k/b/i/p.lyx:Ljava/util/ArrayList;
        //    66: invokevirtual   java/util/ArrayList.iterator:()Ljava/util/Iterator;
        //    69: astore_2       
        //    70: aload_2        
        //    71: invokeinterface java/util/Iterator.hasNext:()Z
        //    76: ifeq            99
        //    79: aload_2        
        //    80: invokeinterface java/util/Iterator.next:()Ljava/lang/Object;
        //    85: checkcast       Ljava/lang/String;
        //    88: astore_3       
        //    89: aload_1        
        //    90: aload_3        
        //    91: invokevirtual   java/io/BufferedWriter.write:(Ljava/lang/String;)V
        //    94: aload_1        
        //    95: invokevirtual   java/io/BufferedWriter.newLine:()V
        //    98: nop            
        //    99: aload_1        
        //   100: invokevirtual   java/io/BufferedWriter.flush:()V
        //   103: aload_1        
        //   104: invokevirtual   java/io/BufferedWriter.close:()V
        //   107: iconst_1       
        //   108: ireturn        
        //   109: astore_0       
        //   110: getstatic       java/lang/System.out:Ljava/io/PrintStream;
        //   113: new             Ljava/lang/StringBuilder;
        //   116: dup            
        //   117: invokespecial   java/lang/StringBuilder.<init>:()V
        //   120: ldc             "Could not write friends.txt: "
        //   122: invokevirtual   java/lang/StringBuilder.append:(Ljava/lang/String;)Ljava/lang/StringBuilder;
        //   125: aload_0        
        //   126: invokevirtual   java/lang/Exception.toString:()Ljava/lang/String;
        //   129: invokevirtual   java/lang/StringBuilder.append:(Ljava/lang/String;)Ljava/lang/StringBuilder;
        //   132: invokevirtual   java/lang/StringBuilder.toString:()Ljava/lang/String;
        //   135: invokevirtual   java/io/PrintStream.println:(Ljava/lang/String;)V
        //   138: aload_0        
        //   139: invokevirtual   java/lang/Exception.printStackTrace:()V
        //   142: getstatic       java/lang/System.out:Ljava/io/PrintStream;
        //   145: getstatic       r/k/b/i/p.lyx:Ljava/util/ArrayList;
        //   148: invokevirtual   java/io/PrintStream.println:(Ljava/lang/Object;)V
        //   151: iconst_0       
        //   152: ireturn        
        //    Exceptions:
        //  Try           Handler
        //  Start  End    Start  End    Type                 
        //  -----  -----  -----  -----  ---------------------
        //  24     99     109    153    Ljava/lang/Exception;
        //  99     108    109    153    Ljava/lang/Exception;
        // 
        throw new IllegalStateException("An error occurred while decompiling this method.");
    }
    
    public static boolean kf() {
        // 
        // This method could not be decompiled.
        // 
        // Original Bytecode:
        // 
        //     1: goto            6
        //     4: iconst_0       
        //     5: ireturn        
        //     6: nop            
        //     7: nop            
        //     8: new             Ljava/util/ArrayList;
        //    11: dup            
        //    12: invokespecial   java/util/ArrayList.<init>:()V
        //    15: putstatic       r/k/b/i/p.lyx:Ljava/util/ArrayList;
        //    18: aload_0        
        //    19: invokevirtual   java/io/BufferedReader.readLine:()Ljava/lang/String;
        //    22: dup            
        //    23: astore_1       
        //    24: ifnull          36
        //    27: getstatic       r/k/b/i/p.lyx:Ljava/util/ArrayList;
        //    30: aload_1        
        //    31: invokevirtual   java/util/ArrayList.add:(Ljava/lang/Object;)Z
        //    34: pop            
        //    35: nop            
        //    36: aload_0        
        //    37: invokevirtual   java/io/BufferedReader.close:()V
        //    40: getstatic       java/lang/System.out:Ljava/io/PrintStream;
        //    43: new             Ljava/lang/StringBuilder;
        //    46: dup            
        //    47: invokespecial   java/lang/StringBuilder.<init>:()V
        //    50: ldc             "Successfully read friends: "
        //    52: invokevirtual   java/lang/StringBuilder.append:(Ljava/lang/String;)Ljava/lang/StringBuilder;
        //    55: getstatic       r/k/b/i/p.lyx:Ljava/util/ArrayList;
        //    58: invokevirtual   java/util/ArrayList.toString:()Ljava/lang/String;
        //    61: invokevirtual   java/lang/StringBuilder.append:(Ljava/lang/String;)Ljava/lang/StringBuilder;
        //    64: invokevirtual   java/lang/StringBuilder.toString:()Ljava/lang/String;
        //    67: invokevirtual   java/io/PrintStream.println:(Ljava/lang/String;)V
        //    70: iconst_1       
        //    71: ireturn        
        //    72: astore_0       
        //    73: new             Ljava/io/File;
        //    76: dup            
        //    77: getstatic       r/k/b/i/p.lyy:Ljava/lang/String;
        //    80: invokespecial   java/io/File.<init>:(Ljava/lang/String;)V
        //    83: astore_1       
        //    84: aload_1        
        //    85: invokevirtual   java/io/File.createNewFile:()Z
        //    88: pop            
        //    89: new             Lr/k/b/i/p$p;
        //    92: dup            
        //    93: invokespecial   r/k/b/i/p$p.<init>:()V
        //    96: putstatic       r/k/b/i/p.lyx:Ljava/util/ArrayList;
        //    99: iconst_1       
        //   100: ireturn        
        //   101: astore_0       
        //   102: getstatic       java/lang/System.out:Ljava/io/PrintStream;
        //   105: new             Ljava/lang/StringBuilder;
        //   108: dup            
        //   109: invokespecial   java/lang/StringBuilder.<init>:()V
        //   112: ldc             "Could not read friends: "
        //   114: invokevirtual   java/lang/StringBuilder.append:(Ljava/lang/String;)Ljava/lang/StringBuilder;
        //   117: aload_0        
        //   118: invokevirtual   java/lang/Exception.toString:()Ljava/lang/String;
        //   121: invokevirtual   java/lang/StringBuilder.append:(Ljava/lang/String;)Ljava/lang/StringBuilder;
        //   124: invokevirtual   java/lang/StringBuilder.toString:()Ljava/lang/String;
        //   127: invokevirtual   java/io/PrintStream.println:(Ljava/lang/String;)V
        //   130: aload_0        
        //   131: invokevirtual   java/lang/Exception.printStackTrace:()V
        //   134: iconst_0       
        //   135: ireturn        
        //    Exceptions:
        //  Try           Handler
        //  Start  End    Start  End    Type                           
        //  -----  -----  -----  -----  -------------------------------
        //  8      18     72     101    Ljava/io/FileNotFoundException;
        //  18     36     72     101    Ljava/io/FileNotFoundException;
        //  36     71     72     101    Ljava/io/FileNotFoundException;
        //  8      18     101    136    Ljava/lang/Exception;
        //  18     36     101    136    Ljava/lang/Exception;
        //  36     71     101    136    Ljava/lang/Exception;
        //  72     100    101    136    Ljava/lang/Exception;
        // 
        throw new IllegalStateException("An error occurred while decompiling this method.");
    }
    
    public static ArrayList<String> kb() {
        return p.lyx;
    }
    
    public static void st(final String s) {
        if (p.lyx == null) {
            return;
        }
        p.lyx.add(s);
    }
    
    public static void sn(final String s) {
        if (p.lyx == null) {
            return;
        }
        p.lyx.remove(s);
    }
    
    public static boolean si(final String s) {
        return p.lyx != null && p.lyx.contains(s);
    }
    
    public static boolean l(final EntityPlayer entityPlayer) {
        return p.lyx != null && (h.mc.player.getUniqueID().equals(entityPlayer.getUniqueID()) || si(entityPlayer.getName()));
    }
    
    static {
        lyy = c.v(42);
    }
}
